PyFSMwDB/CustomExceptions.py
PyFSMwDB/Database.py
PyFSMwDB/FSM.py
PyFSMwDB/Logic.py
PyFSMwDB/State.py
PyFSMwDB/__init__.py
finite_state_machine_lib/CustomExceptions.py
finite_state_machine_lib/Database.py
finite_state_machine_lib/FSM.py
finite_state_machine_lib/Logic.py
finite_state_machine_lib/State.py
finite_state_machine_lib/__init__.py
PyFSMwDB-1.0.0.dist-info/METADATA
PyFSMwDB-1.0.0.dist-info/WHEEL
PyFSMwDB-1.0.0.dist-info/top_level.txt
PyFSMwDB-1.0.0.dist-info/RECORD
