Metadata-Version: 2.1
Name: PyFSMwDB
Version: 1.0.0
Summary: A python lib for FSM with DB
Author: Arian Asghari, Andreas Söderman, Felix Mårtensson, Mattias Öz
License: The MIT Open Source License (MIT)
Requires-Python: >=3.10
Requires-Dist: setuptools (>=66.1.0)
Requires-Dist: influxdb (~=5.3.1)
Requires-Dist: Columnar (~=1.4.1)
